{ "lines": [ { "lineNumber": 9, "timeText": "00:03:15,178 --> 00:03:16,429", "timeEpoch": { "from": 195178, "to": 196429 }, "speech": [ "<font color=\"#696969\">\"Harry Potter.\"</font>" ], "tokens": { "Harry": { "global": 1, "local": 1 } }, "switchCount": 0 }, { "lineNumber": 10, "timeText": "00:03:16,846 --> 00:03:18,514", "timeEpoch": { "from": 196846, "to": 198514 }, "speech": [ "<font color=\"#696969\">Who's Harry Potter?</font>" ], "tokens": { "Harry": { "global": 2, "local": 1 } }, "switchCount": 0 }, { "lineNumber": 17, "timeText": "00:03:45,414 --> 00:03:48,229", "timeEpoch": { "from": 225414, "to": 228229 }, "speech": [ "<font color=\"#696969\">You can tell me all about", "that tosser Harry Potter.</font>" ], "tokens": { "Harry": { "global": 3, "local": 1 } }, "switchCount": 0 }, { "lineNumber": 18, "timeText": "00:04:39,110 --> 00:04:41,299", "timeEpoch": { "from": 279110, "to": 281299 }, "speech": [ "<font color=\"#696969\">You've been reckless this summer, Harry.</font>" ], "tokens": { "Harry": { "global": 4, "local": 1 } }, "switchCount": 0 }, { "lineNumber": 31, "timeText": "00:05:33,536 --> 00:05:37,810", "timeEpoch": { "from": 333536, "to": 337810 }, "speech": [ "<font color=\"#696969\">Harry, I assume, right about now, you're wondering why I brought you here.</font>" ], "tokens": { "Harry": { "global": 5, "local": 1 } }, "switchCount": 0 }, { "lineNumber": 34, "timeText": "00:05:47,820 --> 00:05:49,696", "timeEpoch": { "from": 347820, "to": 349696 }, "speech": [ "<font color=\"#696969\">Wands out, Harry.</font>" ], "tokens": { "Harry": { "global": 6, "local": 1 } }, "switchCount": 0 }, { "lineNumber": 38, "timeText": "00:07:10,814 --> 00:07:13,107", "timeEpoch": { "from": 430814, "to": 433107 }, "speech": [ "<font color=\"#696969\">No need to disfigure me, Albus.</font>" ], "tokens": { "Dumbledore": { "global": 1, "local": 1 } }, "switchCount": 0 }, { "lineNumber": 43, "timeText": "00:07:28,851 --> 00:07:32,917", "timeEpoch": { "from": 448851, "to": 452917 }, "speech": [ "<font color=\"#696969\">Harry, I'd like you to meet an old friend and colleague of mine....</font>" ], "tokens": { "Harry": { "global": 7, "local": 1 } }, "switchCount": 0 }, { "lineNumber": 47, "timeText": "00:07:39,695 --> 00:07:41,988", "timeEpoch": { "from": 459695, "to": 461988 }, "speech": [ "<font color=\"#696969\">Harry Potter.</font>" ], "tokens": { "Harry": { "global": 8, "local": 1 } }, "switchCount": 0 }, { "lineNumber": 58, "timeText": "00:08:50,594 --> 00:08:53,200", "timeEpoch": { "from": 530594, "to": 533200 }, "speech": [ "<font color=\"#696969\">Don't think I don't know", "why you're here, Albus.</font>" ], "tokens": { "Dumbledore": { "global": 2, "local": 1 } }, "switchCount": 0 }, { "lineNumber": 88, "timeText": "00:10:48,725 --> 00:10:51,748", "timeEpoch": { "from": 648725, "to": 651748 }, "speech": [ "<font color=\"#696969\">You're like my friend Mr. Potter here, one of a kind.</font>" ], "tokens": { "Harry": { "global": 9, "local": 1 } }, "switchCount": 0 }, { "lineNumber": 97, "timeText": "00:11:33,245 --> 00:11:36,686", "timeEpoch": { "from": 693245, "to": 696686 }, "speech": [ "<font color=\"#696969\">Professor Slughorn is gonna try to collect you, Harry.</font>" ], "tokens": { "Harry": { "global": 10, "local": 1 } }, "switchCount": 0 }, { "lineNumber": 100, "timeText": "00:11:45,652 --> 00:11:48,780", "timeEpoch": { "from": 705652, "to": 708780 }, "speech": [ "<font color=\"#696969\">I fear I may have stolen", "a wondrous night from you, Harry.</font>" ], "tokens": { "Harry": { "global": 11, "local": 1 } }, "switchCount": 0 }, { "lineNumber": 103, "timeText": "00:11:57,747 --> 00:12:01,396", "timeEpoch": { "from": 717747, "to": 721396 }, "speech": [ "<font color=\"#696969\">Oh, you'll not be returning to Little Whinging tonight, Harry.</font>" ], "tokens": { "Harry": { "global": 12, "local": 1 } }, "switchCount": 0 }, { "lineNumber": 109, "timeText": "00:12:49,462 --> 00:12:51,756", "timeEpoch": { "from": 769462, "to": 771756 }, "speech": [ "<font color=\"#696969\">I was only wondering", "when Harry got here.</font>" ], "tokens": { "Harry": { "global": 13, "local": 1 } }, "switchCount": 0 }, { "lineNumber": 110, "timeText": "00:12:51,860 --> 00:12:55,092", "timeEpoch": { "from": 771860, "to": 775092 }, "speech": [ "<font color=\"#696969\">~ What? Harry? Harry who?", "~ Harry Potter, of course.</font>" ], "tokens": { "Harry": { "global": 16, "local": 3 } }, "switchCount": 0 }, { "lineNumber": 111, "timeText": "00:12:55,301 --> 00:12:58,429", "timeEpoch": { "from": 775301, "to": 778429 }, "speech": [ "<font color=\"#696969\">I think I'd know if Harry Potter was in my house, wouldn't I?</font>" ], "tokens": { "Harry": { "global": 17, "local": 1 } }, "switchCount": 0 }, { "lineNumber": 113, "timeText": "00:13:04,789 --> 00:13:06,457", "timeEpoch": { "from": 784789, "to": 786457 }, "speech": [ "<font color=\"#696969\">Harry? Did someone say \"Harry\"?</font>" ], "tokens": { "Harry": { "global": 19, "local": 2 } }, "switchCount": 0 }, { "lineNumber": 119, "timeText": "00:13:18,551 --> 00:13:20,115", "timeEpoch": { "from": 798551, "to": 800115 }, "speech": [ "<font color=\"#696969\">Harry!</font>" ], "tokens": { "Harry": { "global": 20, "local": 1 } }, "switchCount": 0 }, { "lineNumber": 120, "timeText": "00:13:26,371 --> 00:13:28,039", "timeEpoch": { "from": 806371, "to": 808039 }, "speech": [ "<font color=\"#696969\">Harry!</font>" ], "tokens": { "Harry": { "global": 21, "local": 1 } }, "switchCount": 0 }, { "lineNumber": 124, "timeText": "00:13:37,840 --> 00:13:40,655", "timeEpoch": { "from": 817840, "to": 820655 }, "speech": [ "<font color=\"#696969\">~ I didn't know. Dumbledore.", "~ Oh, that man.</font>" ], "tokens": { "Dumbledore": { "global": 3, "local": 1 } }, "isSwitch": true, "switchCount": 1 }, { "lineNumber": 137, "timeText": "00:14:24,133 --> 00:14:28,095", "timeEpoch": { "from": 864133, "to": 868095 }, "speech": [ "<font color=\"#696969\">But this is Hogwarts we're talking about. It's Dumbledore. What could be safer?</font>" ], "tokens": { "Dumbledore": { "global": 4, "local": 1 } }, "isSwitch": true, "switchCount": 2 }, { "lineNumber": 139, "timeText": "00:14:32,683 --> 00:14:34,351", "timeEpoch": { "from": 872683, "to": 874351 }, "speech": [ "<font color=\"#696969\">....Dumbledore's got a bit old.</font>" ], "tokens": { "Dumbledore": { "global": 5, "local": 1 } }, "isSwitch": true, "switchCount": 3 }, { "lineNumber": 157, "timeText": "00:16:23,828 --> 00:16:27,790", "timeEpoch": { "from": 983828, "to": 987790 }, "speech": [ "<font color=\"#696969\">Dumbledore is a great wizard. Only a fool would question it.</font>" ], "tokens": { "Dumbledore": { "global": 6, "local": 1 } }, "isSwitch": true, "switchCount": 4 }, { "lineNumber": 204, "timeText": "00:19:59,445 --> 00:20:00,905", "timeEpoch": { "from": 1199445, "to": 1200905 }, "speech": [ "<font color=\"#696969\">Hi, Ron.</font>" ], "tokens": { "Ron": { "global": 1, "local": 1 } }, "switchCount": 4 }, { "lineNumber": 211, "timeText": "00:20:44,070 --> 00:20:45,425", "timeEpoch": { "from": 1244070, "to": 1245425 }, "speech": [ "<font color=\"#696969\">Harry?</font>" ], "tokens": { "Harry": { "global": 22, "local": 1 } }, "switchCount": 4 }, { "lineNumber": 224, "timeText": "00:23:17,963 --> 00:23:19,840", "timeEpoch": { "from": 1397963, "to": 1399840 }, "speech": [ "<font color=\"#696969\">Stop it, Harry.", "I know where you're going.</font>" ], "tokens": { "Harry": { "global": 23, "local": 1 } }, "switchCount": 4 }, { "lineNumber": 227, "timeText": "00:23:24,949 --> 00:23:28,389", "timeEpoch": { "from": 1404949, "to": 1408389 }, "speech": [ "<font color=\"#696969\">Harry is under the impression Draco Malfoy is now a Death Eater.</font>" ], "tokens": { "Harry": { "global": 24, "local": 1 } }, "switchCount": 4 }, { "lineNumber": 233, "timeText": "00:23:43,299 --> 00:23:44,863", "timeEpoch": { "from": 1423299, "to": 1424863 }, "speech": [ "<font color=\"#696969\">Hermione saw it with her own eyes.</font>" ], "tokens": { "Hermione": { "global": 1, "local": 1 } }, "switchCount": 4 }, { "lineNumber": 248, "timeText": "00:25:42,785 --> 00:25:44,036", "timeEpoch": { "from": 1542785, "to": 1544036 }, "speech": [ "<font color=\"#696969\">Where's Harry?</font>" ], "tokens": { "Harry": { "global": 25, "local": 1 } }, "switchCount": 4 }, { "lineNumber": 250, "timeText": "00:26:02,908 --> 00:26:06,349", "timeEpoch": { "from": 1562908, "to": 1566349 }, "speech": [ "<font color=\"#696969\">Didn't Mummy ever tell you", "it was rude to eavesdrop, Potter?</font>" ], "tokens": { "Harry": { "global": 26, "local": 1 } }, "switchCount": 4 }, { "lineNumber": 256, "timeText": "00:27:24,859 --> 00:27:26,215", "timeEpoch": { "from": 1644859, "to": 1646215 }, "speech": [ "<font color=\"#696969\">~ Hello, Harry.", "~ Luna!</font>" ], "tokens": { "Harry": { "global": 27, "local": 1 } }, "switchCount": 4 }, { "lineNumber": 265, "timeText": "00:27:57,598 --> 00:27:59,683", "timeEpoch": { "from": 1677598, "to": 1679683 }, "speech": [ "<font color=\"#696969\">No exceptions, Potter.</font>" ], "tokens": { "Harry": { "global": 28, "local": 1 } }, "switchCount": 4 }, { "lineNumber": 273, "timeText": "00:28:29,920 --> 00:28:31,797", "timeEpoch": { "from": 1709920, "to": 1711797 }, "speech": [ "<font color=\"#696969\">Nice face, Potter.</font>" ], "tokens": { "Harry": { "global": 29, "local": 1 } }, "switchCount": 4 }, { "lineNumber": 325, "timeText": "00:32:19,821 --> 00:32:21,177", "timeEpoch": { "from": 1939821, "to": 1941177 }, "speech": [ "<font color=\"#696969\">Potter.</font>" ], "tokens": { "Harry": { "global": 30, "local": 1 } }, "switchCount": 4 }, { "lineNumber": 337, "timeText": "00:32:58,190 --> 00:33:03,091", "timeEpoch": { "from": 1978190, "to": 1983091 }, "speech": [ "<font color=\"#696969\">Potter, take Weasley with you. He looks far too happy over there.</font>" ], "tokens": { "Ron": { "global": 2, "local": 1 }, "Harry": { "global": 31, "local": 1 } }, "switchCount": 4 }, { "lineNumber": 343, "timeText": "00:33:17,792 --> 00:33:21,754", "timeEpoch": { "from": 1997792, "to": 2001754 }, "speech": [ "<font color=\"#696969\">Harry, my boy, I was beginning to worry. We've brought someone with us, I see.</font>" ], "tokens": { "Harry": { "global": 32, "local": 1 } }, "switchCount": 4 }, { "lineNumber": 344, "timeText": "00:33:22,379 --> 00:33:23,526", "timeEpoch": { "from": 2002379, "to": 2003526 }, "speech": [ "<font color=\"#696969\">Ron Weasley, sir.</font>" ], "tokens": { "Ron": { "global": 3, "local": 1 } }, "switchCount": 4 }, { "lineNumber": 347, "timeText": "00:33:28,948 --> 00:33:32,076", "timeEpoch": { "from": 2008948, "to": 2012076 }, "speech": [ "<font color=\"#696969\">Any friend of Harry's is a friend of mine. Get your books out.</font>" ], "tokens": { "Harry": { "global": 33, "local": 1 } }, "switchCount": 4 }, { "lineNumber": 348, "timeText": "00:33:32,285 --> 00:33:34,787", "timeEpoch": { "from": 2012285, "to": 2014787 }, "speech": [ "<font color=\"#696969\">I haven't actually got", "my book yet, and nor has Ron.</font>" ], "tokens": { "Ron": { "global": 4, "local": 1 } }, "switchCount": 4 }, { "lineNumber": 392, "timeText": "00:38:05,872 --> 00:38:08,583", "timeEpoch": { "from": 2285872, "to": 2288583 }, "speech": [ "<font color=\"#696969\">Harry, you got my message. Come in.</font>" ], "tokens": { "Harry": { "global": 34, "local": 1 } }, "switchCount": 4 }, { "lineNumber": 410, "timeText": "00:38:59,777 --> 00:39:03,634", "timeEpoch": { "from": 2339777, "to": 2343634 }, "speech": [ "<font color=\"#696969\">In this case,", "pertaining to one individual, Voldemort....</font>" ], "tokens": { "Voldemort": { "global": 1, "local": 1 } }, "isSwitch": true, "switchCount": 5 }, { "lineNumber": 415, "timeText": "00:39:57,226 --> 00:40:01,501", "timeEpoch": { "from": 2397226, "to": 2401501 }, "speech": [ "<font color=\"#696969\">I admit some confusion upon receiving your letter, Mr. Dumbledore.</font>" ], "tokens": { "Dumbledore": { "global": 7, "local": 1 } }, "isSwitch": true, "switchCount": 6 }, { "lineNumber": 473, "timeText": "00:45:31,287 --> 00:45:33,476", "timeEpoch": { "from": 2731287, "to": 2733476 }, "speech": [ "<font color=\"#696969\">No hard feelings, Weasley, all right?</font>" ], "tokens": { "Ron": { "global": 5, "local": 1 } }, "switchCount": 6 }, { "lineNumber": 482, "timeText": "00:46:10,907 --> 00:46:12,575", "timeEpoch": { "from": 2770907, "to": 2772575 }, "speech": [ "<font color=\"#696969\">Come on, Weasley!</font>" ], "tokens": { "Ron": { "global": 6, "local": 1 } }, "switchCount": 6 }, { "lineNumber": 483, "timeText": "00:46:12,784 --> 00:46:14,452", "timeEpoch": { "from": 2772784, "to": 2774452 }, "speech": [ "<font color=\"#696969\">~ Come on, Ron!", "~ Go on, Weasley!</font>" ], "tokens": { "Ron": { "global": 8, "local": 2 } }, "switchCount": 6 }, { "lineNumber": 484, "timeText": "00:46:16,016 --> 00:46:18,935", "timeEpoch": { "from": 2776016, "to": 2778935 }, "speech": [ "<font color=\"#696969\">~ Go on, Weasley!", "~ Yeah, Ron!</font>" ], "tokens": { "Ron": { "global": 10, "local": 2 } }, "switchCount": 6 }, { "lineNumber": 486, "timeText": "00:46:36,869 --> 00:46:38,954", "timeEpoch": { "from": 2796869, "to": 2798954 }, "speech": [ "<font color=\"#696969\">Come on, Ron!</font>" ], "tokens": { "Ron": { "global": 11, "local": 1 } }, "switchCount": 6 }, { "lineNumber": 487, "timeText": "00:46:47,191 --> 00:46:48,859", "timeEpoch": { "from": 2807191, "to": 2808859 }, "speech": [ "<font color=\"#696969\">Come on, Ron.</font>" ], "tokens": { "Ron": { "global": 12, "local": 1 } }, "switchCount": 6 }, { "lineNumber": 488, "timeText": "00:46:49,589 --> 00:46:51,465", "timeEpoch": { "from": 2809589, "to": 2811465 }, "speech": [ "<font color=\"#696969\">Come on, Ron.</font>" ], "tokens": { "Ron": { "global": 13, "local": 1 } }, "switchCount": 6 }, { "lineNumber": 493, "timeText": "00:47:38,801 --> 00:47:41,825", "timeEpoch": { "from": 2858801, "to": 2861825 }, "speech": [ "<font color=\"#696969\">He's got a bit of a thing for you, Hermione. Cormac.</font>" ], "tokens": { "Hermione": { "global": 2, "local": 1 } }, "switchCount": 6 }, { "lineNumber": 499, "timeText": "00:48:00,488 --> 00:48:04,658", "timeEpoch": { "from": 2880488, "to": 2884658 }, "speech": [ "<font color=\"#696969\">He's even better than you, Hermione. Slughorn thinks he's a genius.</font>" ], "tokens": { "Hermione": { "global": 3, "local": 1 } }, "switchCount": 6 }, { "lineNumber": 513, "timeText": "00:49:01,795 --> 00:49:03,776", "timeEpoch": { "from": 2941795, "to": 2943776 }, "speech": [ "<font color=\"#696969\">It's just like being with Hermione.</font>" ], "tokens": { "Hermione": { "global": 4, "local": 1 } }, "switchCount": 6 }, { "lineNumber": 531, "timeText": "00:50:10,192 --> 00:50:12,903", "timeEpoch": { "from": 3010192, "to": 3012903 }, "speech": [ "<font color=\"#696969\">Honestly, Ronald,", "they're only holding hands.</font>" ], "tokens": { "Ron": { "global": 14, "local": 1 } }, "switchCount": 6 }, { "lineNumber": 550, "timeText": "00:51:19,319 --> 00:51:21,613", "timeEpoch": { "from": 3079319, "to": 3081613 }, "speech": [ "<font color=\"#696969\">Dumbledore's asked me", "to get to know him.</font>" ], "tokens": { "Dumbledore": { "global": 8, "local": 1 } }, "isSwitch": true, "switchCount": 7 }, { "lineNumber": 552, "timeText": "00:51:23,906 --> 00:51:27,660", "timeEpoch": { "from": 3083906, "to": 3087660 }, "speech": [ "<font color=\"#696969\">It must be important.", "If it wasn't, Dumbledore wouldn't ask.</font>" ], "tokens": { "Dumbledore": { "global": 9, "local": 1 } }, "isSwitch": true, "switchCount": 8 }, { "lineNumber": 555, "timeText": "00:51:48,304 --> 00:51:49,764", "timeEpoch": { "from": 3108304, "to": 3109764 }, "speech": [ "<font color=\"#696969\">~ Harry.", "~ What?</font>" ], "tokens": { "Harry": { "global": 35, "local": 1 } }, "switchCount": 8 }, { "lineNumber": 566, "timeText": "00:53:18,179 --> 00:53:21,724", "timeEpoch": { "from": 3198179, "to": 3201724 }, "speech": [ "<font color=\"#696969\">~ Did she say to whom?", "~ To Professor Dumbledore.</font>" ], "tokens": { "Dumbledore": { "global": 10, "local": 1 } }, "isSwitch": true, "switchCount": 9 }, { "lineNumber": 575, "timeText": "00:54:02,596 --> 00:54:06,141", "timeEpoch": { "from": 3242596, "to": 3246141 }, "speech": [ "<font color=\"#696969\">If she was delivering that to Dumbledore, she wasn't doing it knowingly.</font>" ], "tokens": { "Dumbledore": { "global": 11, "local": 1 } }, "isSwitch": true, "switchCount": 10 }, { "lineNumber": 578, "timeText": "00:54:12,605 --> 00:54:16,463", "timeEpoch": { "from": 3252605, "to": 3256463 }, "speech": [ "<font color=\"#696969\">That is a very serious accusation, Potter.</font>" ], "tokens": { "Harry": { "global": 36, "local": 1 } }, "switchCount": 10 }, { "lineNumber": 583, "timeText": "00:54:30,747 --> 00:54:32,728", "timeEpoch": { "from": 3270747, "to": 3272728 }, "speech": [ "<font color=\"#696969\">You astonish with your gifts, Potter.</font>" ], "tokens": { "Harry": { "global": 37, "local": 1 } }, "switchCount": 10 }, { "lineNumber": 600, "timeText": "00:55:51,030 --> 00:55:52,802", "timeEpoch": { "from": 3351030, "to": 3352802 }, "speech": [ "<font color=\"#696969\">Hermione's got nice skin.</font>" ], "tokens": { "Hermione": { "global": 5, "local": 1 } }, "switchCount": 10 }, { "lineNumber": 622, "timeText": "00:57:25,284 --> 00:57:28,933", "timeEpoch": { "from": 3445284, "to": 3448933 }, "speech": [ "<font color=\"#696969\">Ah. Miss Weasley. Come in, come in.</font>" ], "tokens": { "Ron": { "global": 15, "local": 1 } }, "switchCount": 10 }, { "lineNumber": 629, "timeText": "00:58:12,828 --> 00:58:14,497", "timeEpoch": { "from": 3492828, "to": 3494497 }, "speech": [ "<font color=\"#696969\">~ Potter.", "~ I'm sorry, sir.</font>" ], "tokens": { "Harry": { "global": 38, "local": 1 } }, "switchCount": 10 }, { "lineNumber": 641, "timeText": "00:58:49,112 --> 00:58:52,970", "timeEpoch": { "from": 3529112, "to": 3532970 }, "speech": [ "<font color=\"#696969\">But then again, you already are someone, aren't you, Harry?</font>" ], "tokens": { "Harry": { "global": 39, "local": 1 } }, "switchCount": 10 }, { "lineNumber": 642, "timeText": "00:58:54,534 --> 00:58:56,515", "timeEpoch": { "from": 3534534, "to": 3536515 }, "speech": [ "<font color=\"#696969\">Did Voldemort ever make the shelf, sir?</font>" ], "tokens": { "Voldemort": { "global": 2, "local": 1 } }, "isSwitch": true, "switchCount": 11 }, { "lineNumber": 650, "timeText": "00:59:27,064 --> 00:59:29,879", "timeEpoch": { "from": 3567064, "to": 3569879 }, "speech": [ "<font color=\"#696969\">But I'm afraid I must disappoint you, Harry.</font>" ], "tokens": { "Harry": { "global": 40, "local": 1 } }, "switchCount": 11 }, { "lineNumber": 657, "timeText": "01:00:05,642 --> 01:00:07,101", "timeEpoch": { "from": 3605642, "to": 3607101 }, "speech": [ "<font color=\"#696969\">Good luck, eh, Ron.</font>" ], "tokens": { "Ron": { "global": 16, "local": 1 } }, "switchCount": 11 }, { "lineNumber": 658, "timeText": "01:00:08,561 --> 01:00:10,959", "timeEpoch": { "from": 3608561, "to": 3610959 }, "speech": [ "<font color=\"#696969\">~ Nice hat!", "~ Ron, you're a loser.</font>" ], "tokens": { "Ron": { "global": 17, "local": 1 } }, "switchCount": 11 }, { "lineNumber": 659, "timeText": "01:00:11,168 --> 01:00:14,191", "timeEpoch": { "from": 3611168, "to": 3614191 }, "speech": [ "<font color=\"#696969\">I'm counting on you, Ron.", "I have two Galleons on Gryffindor, yeah?</font>" ], "tokens": { "Ron": { "global": 18, "local": 1 } }, "switchCount": 11 }, { "lineNumber": 660, "timeText": "01:00:14,400 --> 01:00:16,694", "timeEpoch": { "from": 3614400, "to": 3616694 }, "speech": [ "<font color=\"#696969\">~ Looking good, Ron.", "~ Loser!</font>" ], "tokens": { "Ron": { "global": 19, "local": 1 } }, "switchCount": 11 }, { "lineNumber": 665, "timeText": "01:00:37,025 --> 01:00:39,423", "timeEpoch": { "from": 3637025, "to": 3639423 }, "speech": [ "<font color=\"#696969\">Though I think Harry enjoyed dessert.</font>" ], "tokens": { "Harry": { "global": 41, "local": 1 } }, "switchCount": 11 }, { "lineNumber": 670, "timeText": "01:00:56,939 --> 01:00:59,025", "timeEpoch": { "from": 3656939, "to": 3659025 }, "speech": [ "<font color=\"#696969\">Good luck today, Ron.</font>" ], "tokens": { "Ron": { "global": 20, "local": 1 } }, "switchCount": 11 }, { "lineNumber": 676, "timeText": "01:01:16,437 --> 01:01:18,522", "timeEpoch": { "from": 3676437, "to": 3678522 }, "speech": [ "<font color=\"#696969\">You look dreadful, Ron.</font>" ], "tokens": { "Ron": { "global": 21, "local": 1 } }, "switchCount": 11 }, { "lineNumber": 680, "timeText": "01:01:31,346 --> 01:01:33,015", "timeEpoch": { "from": 3691346, "to": 3693015 }, "speech": [ "<font color=\"#696969\">Don't drink it, Ron.</font>" ], "tokens": { "Ron": { "global": 22, "local": 1 } }, "switchCount": 11 }, { "lineNumber": 682, "timeText": "01:01:46,152 --> 01:01:48,863", "timeEpoch": { "from": 3706152, "to": 3708863 }, "speech": [ "<font color=\"#696969\">Come on, Harry.", "We've got a game to win.</font>" ], "tokens": { "Harry": { "global": 42, "local": 1 } }, "switchCount": 11 }, { "lineNumber": 684, "timeText": "01:02:14,929 --> 01:02:17,848", "timeEpoch": { "from": 3734929, "to": 3737848 }, "speech": [ "<font color=\"#696969\">Go on, Ron! Do it!</font>" ], "tokens": { "Ron": { "global": 23, "local": 1 } }, "switchCount": 11 }, { "lineNumber": 685, "timeText": "01:02:51,734 --> 01:02:54,027", "timeEpoch": { "from": 3771734, "to": 3774027 }, "speech": [ "<font color=\"#696969\">Weasley! Weasley! Weasley!</font>" ], "tokens": { "Ron": { "global": 26, "local": 3 } }, "switchCount": 11 }, { "lineNumber": 687, "timeText": "01:02:56,008 --> 01:02:59,553", "timeEpoch": { "from": 3776008, "to": 3779553 }, "speech": [ "<font color=\"#696969\">Weasley! Weasley! Weasley!</font>" ], "tokens": { "Ron": { "global": 29, "local": 3 } }, "switchCount": 11 }, { "lineNumber": 690, "timeText": "01:03:09,771 --> 01:03:14,880", "timeEpoch": { "from": 3789771, "to": 3794880 }, "speech": [ "<font color=\"#696969\">Weasley! Weasley! Weasley!</font>" ], "tokens": { "Ron": { "global": 32, "local": 3 } }, "switchCount": 11 }, { "lineNumber": 695, "timeText": "01:03:37,818 --> 01:03:39,695", "timeEpoch": { "from": 3817818, "to": 3819695 }, "speech": [ "<font color=\"#696969\">Ron only thought you did.</font>" ], "tokens": { "Ron": { "global": 33, "local": 1 } }, "switchCount": 11 }, { "lineNumber": 698, "timeText": "01:04:42,045 --> 01:04:44,026", "timeEpoch": { "from": 3882045, "to": 3884026 }, "speech": [ "<font color=\"#696969\">How does it feel, Harry?</font>" ], "tokens": { "Harry": { "global": 43, "local": 1 } }, "switchCount": 11 }, { "lineNumber": 744, "timeText": "01:09:39,196 --> 01:09:42,115", "timeEpoch": { "from": 4179196, "to": 4182115 }, "speech": [ "<font color=\"#696969\">Hermione. What are you doing? And what happened to you?</font>" ], "tokens": { "Hermione": { "global": 6, "local": 1 } }, "switchCount": 11 }, { "lineNumber": 747, "timeText": "01:09:50,978 --> 01:09:53,480", "timeEpoch": { "from": 4190978, "to": 4193480 }, "speech": [ "<font color=\"#696969\">I thought it would annoy Ron the most.</font>" ], "tokens": { "Ron": { "global": 34, "local": 1 } }, "switchCount": 11 }, { "lineNumber": 761, "timeText": "01:10:44,986 --> 01:10:48,844", "timeEpoch": { "from": 4244986, "to": 4248844 }, "speech": [ "<font color=\"#696969\">Not so quick, Potter.</font>" ], "tokens": { "Harry": { "global": 44, "local": 1 } }, "switchCount": 11 }, { "lineNumber": 765, "timeText": "01:11:00,626 --> 01:11:02,920", "timeEpoch": { "from": 4260626, "to": 4262920 }, "speech": [ "<font color=\"#696969\">~ A message?", "~ From Professor Dumbledore.</font>" ], "tokens": { "Dumbledore": { "global": 12, "local": 1 } }, "isSwitch": true, "switchCount": 12 }, { "lineNumber": 801, "timeText": "01:14:03,713 --> 01:14:07,049", "timeEpoch": { "from": 4443713, "to": 4447049 }, "speech": [ "<font color=\"#696969\">Voldemort has chosen", "Draco Malfoy for a mission?</font>" ], "tokens": { "Voldemort": { "global": 3, "local": 1 } }, "isSwitch": true, "switchCount": 13 }, { "lineNumber": 805, "timeText": "01:14:14,765 --> 01:14:17,788", "timeEpoch": { "from": 4454765, "to": 4457788 }, "speech": [ "<font color=\"#696969\">~ That's not what it sounded like.", "~ Perhaps Harry's right.</font>" ], "tokens": { "Harry": { "global": 45, "local": 1 } }, "switchCount": 13 }, { "lineNumber": 807, "timeText": "01:14:20,082 --> 01:14:23,627", "timeEpoch": { "from": 4460082, "to": 4463627 }, "speech": [ "<font color=\"#696969\">It comes down to whether or not you trust Dumbledore's judgment.</font>" ], "tokens": { "Dumbledore": { "global": 13, "local": 1 } }, "isSwitch": true, "switchCount": 14 }, { "lineNumber": 808, "timeText": "01:14:23,836 --> 01:14:27,902", "timeEpoch": { "from": 4463836, "to": 4467902 }, "speech": [ "<font color=\"#696969\">~ Dumbledore trusts Snape, therefore I do.", "~ Dumbledore can make mistakes.</font>" ], "tokens": { "Dumbledore": { "global": 15, "local": 2 } }, "isSwitch": true, "switchCount": 16 }, { "lineNumber": 811, "timeText": "01:14:33,219 --> 01:14:36,139", "timeEpoch": { "from": 4473219, "to": 4476139 }, "speech": [ "<font color=\"#696969\">People are disappearing, Harry, daily.</font>" ], "tokens": { "Harry": { "global": 46, "local": 1 } }, "switchCount": 16 }, { "lineNumber": 821, "timeText": "01:15:48,915 --> 01:15:50,896", "timeEpoch": { "from": 4548915, "to": 4550896 }, "speech": [ "<font color=\"#696969\">Are you all right, Mr. Weasley?</font>" ], "tokens": { "Ron": { "global": 35, "local": 1 } }, "switchCount": 16 }, { "lineNumber": 827, "timeText": "01:16:06,431 --> 01:16:09,455", "timeEpoch": { "from": 4566431, "to": 4569455 }, "speech": [ "<font color=\"#696969\">If Dumbledore's traveling,", "then that's news to the Ministry....</font>" ], "tokens": { "Dumbledore": { "global": 16, "local": 1 } }, "isSwitch": true, "switchCount": 17 }, { "lineNumber": 828, "timeText": "01:16:09,559 --> 01:16:12,061", "timeEpoch": { "from": 4569559, "to": 4572061 }, "speech": [ "<font color=\"#696969\">....but perhaps that's the way Dumbledore wants it.</font>" ], "tokens": { "Dumbledore": { "global": 17, "local": 1 } }, "isSwitch": true, "switchCount": 18 }, { "lineNumber": 833, "timeText": "01:16:23,426 --> 01:16:25,094", "timeEpoch": { "from": 4583426, "to": 4585094 }, "speech": [ "<font color=\"#696969\">....what you and Ron saw in summer....</font>" ], "tokens": { "Ron": { "global": 36, "local": 1 } }, "switchCount": 18 }, { "lineNumber": 837, "timeText": "01:16:32,706 --> 01:16:36,772", "timeEpoch": { "from": 4592706, "to": 4596772 }, "speech": [ "<font color=\"#696969\">They were all the rage", "when Voldemort first rose to power.</font>" ], "tokens": { "Voldemort": { "global": 4, "local": 1 } }, "isSwitch": true, "switchCount": 19 }, { "lineNumber": 850, "timeText": "01:17:36,515 --> 01:17:38,183", "timeEpoch": { "from": 4656515, "to": 4658183 }, "speech": [ "<font color=\"#696969\">Has Ron gone to bed?</font>" ], "tokens": { "Ron": { "global": 37, "local": 1 } }, "switchCount": 19 }, { "lineNumber": 853, "timeText": "01:17:56,951 --> 01:17:58,827", "timeEpoch": { "from": 4676951, "to": 4678827 }, "speech": [ "<font color=\"#696969\">Merry Christmas, Harry.</font>" ], "tokens": { "Harry": { "global": 47, "local": 1 } }, "switchCount": 19 }, { "lineNumber": 855, "timeText": "01:18:19,055 --> 01:18:21,348", "timeEpoch": { "from": 4699055, "to": 4701348 }, "speech": [ "<font color=\"#696969\">~ Harry, no!", "~ Remus!</font>" ], "tokens": { "Harry": { "global": 48, "local": 1 } }, "switchCount": 19 }, { "lineNumber": 859, "timeText": "01:18:43,974 --> 01:18:47,310", "timeEpoch": { "from": 4723974, "to": 4727310 }, "speech": [ "<font color=\"#696969\">Harry, can you get me?", "You coming to get me?</font>" ], "tokens": { "Harry": { "global": 49, "local": 1 } }, "switchCount": 19 }, { "lineNumber": 860, "timeText": "01:19:17,025 --> 01:19:18,381", "timeEpoch": { "from": 4757025, "to": 4758381 }, "speech": [ "<font color=\"#696969\">Harry?</font>" ], "tokens": { "Harry": { "global": 50, "local": 1 } }, "switchCount": 19 }, { "lineNumber": 862, "timeText": "01:20:00,399 --> 01:20:02,171", "timeEpoch": { "from": 4800399, "to": 4802171 }, "speech": [ "<font color=\"#696969\">Harry!</font>" ], "tokens": { "Harry": { "global": 51, "local": 1 } }, "switchCount": 19 }, { "lineNumber": 866, "timeText": "01:21:12,862 --> 01:21:16,928", "timeEpoch": { "from": 4872862, "to": 4876928 }, "speech": [ "<font color=\"#696969\">You're bloody lucky you weren't killed. You have to realize who you are, Harry.</font>" ], "tokens": { "Harry": { "global": 52, "local": 1 } }, "switchCount": 19 }, { "lineNumber": 867, "timeText": "01:21:17,137 --> 01:21:19,639", "timeEpoch": { "from": 4877137, "to": 4879639 }, "speech": [ "<font color=\"#696969\">I know who I am, Hermione, all right?</font>" ], "tokens": { "Hermione": { "global": 7, "local": 1 } }, "switchCount": 19 }, { "lineNumber": 928, "timeText": "01:25:28,204 --> 01:25:29,559", "timeEpoch": { "from": 5128204, "to": 5129559 }, "speech": [ "<font color=\"#696969\">I'm Potions Master, Harry.</font>" ], "tokens": { "Harry": { "global": 53, "local": 1 } }, "switchCount": 19 }, { "lineNumber": 939, "timeText": "01:26:06,364 --> 01:26:09,388", "timeEpoch": { "from": 5166364, "to": 5169388 }, "speech": [ "<font color=\"#696969\">Dumbledore put you up to this, didn't he?</font>" ], "tokens": { "Dumbledore": { "global": 18, "local": 1 } }, "isSwitch": true, "switchCount": 20 }, { "lineNumber": 942, "timeText": "01:26:22,108 --> 01:26:24,193", "timeEpoch": { "from": 5182108, "to": 5184193 }, "speech": [ "<font color=\"#696969\">Oh, it's you, Potter.</font>" ], "tokens": { "Harry": { "global": 54, "local": 1 } }, "switchCount": 20 }, { "lineNumber": 948, "timeText": "01:26:53,700 --> 01:26:57,141", "timeEpoch": { "from": 5213700, "to": 5217141 }, "speech": [ "<font color=\"#696969\">~ Or 20.", "~ I can't stop thinking about her, Harry.</font>" ], "tokens": { "Harry": { "global": 55, "local": 1 } }, "switchCount": 20 }, { "lineNumber": 962, "timeText": "01:28:05,955 --> 01:28:10,751", "timeEpoch": { "from": 5285955, "to": 5290751 }, "speech": [ "<font color=\"#696969\">Come on, Ron. I'm gonna introduce you to Romilda Vane.</font>" ], "tokens": { "Ron": { "global": 38, "local": 1 } }, "switchCount": 20 }, { "lineNumber": 968, "timeText": "01:28:34,627 --> 01:28:37,859", "timeEpoch": { "from": 5314627, "to": 5317859 }, "speech": [ "<font color=\"#696969\">I'd have thought you could whip up a remedy for this in no time, Harry.</font>" ], "tokens": { "Harry": { "global": 56, "local": 1 } }, "switchCount": 20 }, { "lineNumber": 975, "timeText": "01:29:03,821 --> 01:29:06,428", "timeEpoch": { "from": 5343821, "to": 5346428 }, "speech": [ "<font color=\"#696969\">All the questions about Voldemort.</font>" ], "tokens": { "Voldemort": { "global": 5, "local": 1 } }, "isSwitch": true, "switchCount": 21 }, { "lineNumber": 984, "timeText": "01:29:55,431 --> 01:29:57,100", "timeEpoch": { "from": 5395431, "to": 5397100 }, "speech": [ "<font color=\"#696969\">Here we are, Potter.</font>" ], "tokens": { "Harry": { "global": 57, "local": 1 } }, "switchCount": 21 }, { "lineNumber": 986, "timeText": "01:30:03,668 --> 01:30:04,607", "timeEpoch": { "from": 5403668, "to": 5404607 }, "speech": [ "<font color=\"#696969\">Ron.</font>" ], "tokens": { "Ron": { "global": 39, "local": 1 } }, "switchCount": 21 }, { "lineNumber": 987, "timeText": "01:30:07,109 --> 01:30:10,550", "timeEpoch": { "from": 5407109, "to": 5410550 }, "speech": [ "<font color=\"#696969\">Ron. Professor, do something.</font>" ], "tokens": { "Ron": { "global": 40, "local": 1 } }, "switchCount": 21 }, { "lineNumber": 989, "timeText": "01:30:29,734 --> 01:30:31,507", "timeEpoch": { "from": 5429734, "to": 5431507 }, "speech": [ "<font color=\"#696969\">Come on, Ron, breathe.</font>" ], "tokens": { "Ron": { "global": 41, "local": 1 } }, "switchCount": 21 }, { "lineNumber": 991, "timeText": "01:31:07,582 --> 01:31:10,918", "timeEpoch": { "from": 5467582, "to": 5470918 }, "speech": [ "<font color=\"#696969\">Quick thinking on your part, Harry, using a bezoar.</font>" ], "tokens": { "Harry": { "global": 58, "local": 1 } }, "switchCount": 21 }, { "lineNumber": 994, "timeText": "01:31:17,278 --> 01:31:19,989", "timeEpoch": { "from": 5477278, "to": 5479989 }, "speech": [ "<font color=\"#696969\">I think we agree,", "Potter's actions were heroic.</font>" ], "tokens": { "Harry": { "global": 59, "local": 1 } }, "switchCount": 21 }, { "lineNumber": 1017, "timeText": "01:32:40,689 --> 01:32:43,817", "timeEpoch": { "from": 5560689, "to": 5563817 }, "speech": [ "<font color=\"#696969\">Uh....Hermione....</font>" ], "tokens": { "Hermione": { "global": 8, "local": 1 } }, "switchCount": 21 }, { "lineNumber": 1018, "timeText": "01:32:47,884 --> 01:32:49,865", "timeEpoch": { "from": 5567884, "to": 5569865 }, "speech": [ "<font color=\"#696969\">Hermione.</font>" ], "tokens": { "Hermione": { "global": 9, "local": 1 } }, "switchCount": 21 }, { "lineNumber": 1019, "timeText": "01:32:50,699 --> 01:32:52,888", "timeEpoch": { "from": 5570699, "to": 5572888 }, "speech": [ "<font color=\"#696969\">Hermione.</font>" ], "tokens": { "Hermione": { "global": 10, "local": 1 } }, "switchCount": 21 }, { "lineNumber": 1022, "timeText": "01:33:07,277 --> 01:33:09,883", "timeEpoch": { "from": 5587277, "to": 5589883 }, "speech": [ "<font color=\"#696969\">Mr. Weasley is well tended.</font>" ], "tokens": { "Ron": { "global": 42, "local": 1 } }, "switchCount": 21 }, { "lineNumber": 1026, "timeText": "01:35:37,938 --> 01:35:41,795", "timeEpoch": { "from": 5737938, "to": 5741795 }, "speech": [ "<font color=\"#696969\">Stop it, Ron. You're making it snow.</font>" ], "tokens": { "Ron": { "global": 43, "local": 1 } }, "switchCount": 21 }, { "lineNumber": 1040, "timeText": "01:36:52,486 --> 01:36:53,737", "timeEpoch": { "from": 5812486, "to": 5813737 }, "speech": [ "<font color=\"#696969\">Harry.</font>" ], "tokens": { "Harry": { "global": 60, "local": 1 } }, "switchCount": 21 }, { "lineNumber": 1044, "timeText": "01:37:10,628 --> 01:37:15,111", "timeEpoch": { "from": 5830628, "to": 5835111 }, "speech": [ "<font color=\"#696969\">I know you're going to ask, Harry, but I don't know who cursed me.</font>" ], "tokens": { "Harry": { "global": 61, "local": 1 } }, "switchCount": 21 }, { "lineNumber": 1080, "timeText": "01:43:56,422 --> 01:43:59,133", "timeEpoch": { "from": 6236422, "to": 6239133 }, "speech": [ "<font color=\"#696969\">No, Harry, you've got to go and speak to Slughorn.</font>" ], "tokens": { "Harry": { "global": 62, "local": 1 } }, "switchCount": 21 }, { "lineNumber": 1087, "timeText": "01:44:48,137 --> 01:44:49,805", "timeEpoch": { "from": 6288137, "to": 6289805 }, "speech": [ "<font color=\"#696969\">Merlin's beard, Harry!</font>" ], "tokens": { "Harry": { "global": 63, "local": 1 } }, "switchCount": 21 }, { "lineNumber": 1098, "timeText": "01:45:25,672 --> 01:45:27,861", "timeEpoch": { "from": 6325672, "to": 6327861 }, "speech": [ "<font color=\"#696969\">How did you get out of the castle, Harry?</font>" ], "tokens": { "Harry": { "global": 64, "local": 1 } }, "switchCount": 21 }, { "lineNumber": 1103, "timeText": "01:45:37,036 --> 01:45:38,600", "timeEpoch": { "from": 6337036, "to": 6338600 }, "speech": [ "<font color=\"#696969\">Harry!</font>" ], "tokens": { "Harry": { "global": 65, "local": 1 } }, "switchCount": 21 }, { "lineNumber": 1107, "timeText": "01:45:53,614 --> 01:45:56,847", "timeEpoch": { "from": 6353614, "to": 6356847 }, "speech": [ "<font color=\"#696969\">Harry, I must insist", "you accompany me....</font>" ], "tokens": { "Harry": { "global": 66, "local": 1 } }, "switchCount": 21 }, { "lineNumber": 1176, "timeText": "01:51:00,254 --> 01:51:03,486", "timeEpoch": { "from": 6660254, "to": 6663486 }, "speech": [ "<font color=\"#696969\">Because her love was more powerful than Voldemort.</font>" ], "tokens": { "Voldemort": { "global": 6, "local": 1 } }, "isSwitch": true, "switchCount": 22 }, { "lineNumber": 1236, "timeText": "01:55:48,960 --> 01:55:50,941", "timeEpoch": { "from": 6948960, "to": 6950941 }, "speech": [ "<font color=\"#696969\">~ The ring?", "~ Belonged to Voldemort's mother.</font>" ], "tokens": { "Voldemort": { "global": 7, "local": 1 } }, "isSwitch": true, "switchCount": 23 }, { "lineNumber": 1239, "timeText": "01:56:00,325 --> 01:56:01,471", "timeEpoch": { "from": 6960325, "to": 6961471 }, "speech": [ "<font color=\"#696969\">One destroys Voldemort.</font>" ], "tokens": { "Voldemort": { "global": 8, "local": 1 } }, "isSwitch": true, "switchCount": 24 }, { "lineNumber": 1247, "timeText": "01:56:45,888 --> 01:56:50,475", "timeEpoch": { "from": 7005888, "to": 7010475 }, "speech": [ "<font color=\"#696969\">Once again,", "I must ask too much of you, Harry.</font>" ], "tokens": { "Harry": { "global": 67, "local": 1 } }, "switchCount": 24 }, { "lineNumber": 1253, "timeText": "01:57:32,181 --> 01:57:33,745", "timeEpoch": { "from": 7052181, "to": 7053745 }, "speech": [ "<font color=\"#696969\">Oh, Harry.</font>" ], "tokens": { "Harry": { "global": 68, "local": 1 } }, "switchCount": 24 }, { "lineNumber": 1257, "timeText": "01:57:51,365 --> 01:57:53,763", "timeEpoch": { "from": 7071365, "to": 7073763 }, "speech": [ "<font color=\"#696969\">Forgive my mawkishness, Harry.</font>" ], "tokens": { "Harry": { "global": 69, "local": 1 } }, "switchCount": 24 }, { "lineNumber": 1271, "timeText": "01:58:41,412 --> 01:58:42,976", "timeEpoch": { "from": 7121412, "to": 7122976 }, "speech": [ "<font color=\"#696969\">Your word, Harry.</font>" ], "tokens": { "Harry": { "global": 70, "local": 1 } }, "switchCount": 24 }, { "lineNumber": 1282, "timeText": "02:00:07,846 --> 02:00:09,619", "timeEpoch": { "from": 7207846, "to": 7209619 }, "speech": [ "<font color=\"#696969\">~ You should've let me, sir.", "~ No, Harry.</font>" ], "tokens": { "Harry": { "global": 71, "local": 1 } }, "switchCount": 24 }, { "lineNumber": 1284, "timeText": "02:00:34,746 --> 02:00:39,334", "timeEpoch": { "from": 7234746, "to": 7239334 }, "speech": [ "<font color=\"#696969\">Voldemort will not have made it easy to discover his hiding place.</font>" ], "tokens": { "Voldemort": { "global": 9, "local": 1 } }, "isSwitch": true, "switchCount": 25 }, { "lineNumber": 1289, "timeText": "02:01:37,930 --> 02:01:39,703", "timeEpoch": { "from": 7297930, "to": 7299703 }, "speech": [ "<font color=\"#696969\">If you would, Harry.</font>" ], "tokens": { "Harry": { "global": 72, "local": 1 } }, "switchCount": 25 }, { "lineNumber": 1299, "timeText": "02:03:02,384 --> 02:03:05,929", "timeEpoch": { "from": 7382384, "to": 7385929 }, "speech": [ "<font color=\"#696969\">It's your job, Harry, to make sure I keep drinking this potion.</font>" ], "tokens": { "Harry": { "global": 73, "local": 1 } }, "switchCount": 25 }, { "lineNumber": 1303, "timeText": "02:03:20,734 --> 02:03:22,715", "timeEpoch": { "from": 7400734, "to": 7402715 }, "speech": [ "<font color=\"#696969\">Your good health, Harry.</font>" ], "tokens": { "Harry": { "global": 74, "local": 1 } }, "switchCount": 25 }, { "lineNumber": 1306, "timeText": "02:03:50,241 --> 02:03:51,701", "timeEpoch": { "from": 7430241, "to": 7431701 }, "speech": [ "<font color=\"#696969\">Harry.</font>" ], "tokens": { "Harry": { "global": 75, "local": 1 } }, "switchCount": 25 }, { "lineNumber": 1322, "timeText": "02:05:20,846 --> 02:05:22,306", "timeEpoch": { "from": 7520846, "to": 7522306 }, "speech": [ "<font color=\"#696969\">Harry.</font>" ], "tokens": { "Harry": { "global": 76, "local": 1 } }, "switchCount": 25 }, { "lineNumber": 1328, "timeText": "02:05:46,495 --> 02:05:47,746", "timeEpoch": { "from": 7546495, "to": 7547746 }, "speech": [ "<font color=\"#696969\">Harry.</font>" ], "tokens": { "Harry": { "global": 77, "local": 1 } }, "switchCount": 25 }, { "lineNumber": 1334, "timeText": "02:07:12,929 --> 02:07:14,702", "timeEpoch": { "from": 7632929, "to": 7634702 }, "speech": [ "<font color=\"#696969\">Harry.</font>" ], "tokens": { "Harry": { "global": 78, "local": 1 } }, "switchCount": 25 }, { "lineNumber": 1336, "timeText": "02:07:20,124 --> 02:07:21,270", "timeEpoch": { "from": 7640124, "to": 7641270 }, "speech": [ "<font color=\"#696969\">Harry.</font>" ], "tokens": { "Harry": { "global": 79, "local": 1 } }, "switchCount": 25 }, { "lineNumber": 1337, "timeText": "02:07:22,209 --> 02:07:23,773", "timeEpoch": { "from": 7642209, "to": 7643773 }, "speech": [ "<font color=\"#696969\">~ Stupefy!", "~ Harry.</font>" ], "tokens": { "Harry": { "global": 80, "local": 1 } }, "switchCount": 25 }, { "lineNumber": 1338, "timeText": "02:08:22,995 --> 02:08:24,246", "timeEpoch": { "from": 7702995, "to": 7704246 }, "speech": [ "<font color=\"#696969\">Harry.</font>" ], "tokens": { "Harry": { "global": 81, "local": 1 } }, "switchCount": 25 }, { "lineNumber": 1346, "timeText": "02:10:14,557 --> 02:10:16,746", "timeEpoch": { "from": 7814557, "to": 7816746 }, "speech": [ "<font color=\"#696969\">Severus, Harry.</font>" ], "tokens": { "Harry": { "global": 82, "local": 1 } }, "switchCount": 25 }, { "lineNumber": 1347, "timeText": "02:10:22,064 --> 02:10:24,462", "timeEpoch": { "from": 7822064, "to": 7824462 }, "speech": [ "<font color=\"#696969\">Hide yourself below, Harry.</font>" ], "tokens": { "Harry": { "global": 83, "local": 1 } }, "switchCount": 25 }, { "lineNumber": 1350, "timeText": "02:10:33,637 --> 02:10:35,305", "timeEpoch": { "from": 7833637, "to": 7835305 }, "speech": [ "<font color=\"#696969\">Harry, do as I say.</font>" ], "tokens": { "Harry": { "global": 84, "local": 1 } }, "switchCount": 25 }, { "lineNumber": 1388, "timeText": "02:13:12,743 --> 02:13:17,852", "timeEpoch": { "from": 7992743, "to": 7997852 }, "speech": [ "<font color=\"#696969\">Love to, Albus, but I'm afraid we're all on a bit of a tight schedule.</font>" ], "tokens": { "Dumbledore": { "global": 19, "local": 1 } }, "switchCount": 25 }, { "lineNumber": 1408, "timeText": "02:16:06,029 --> 02:16:11,243", "timeEpoch": { "from": 8166029, "to": 8171243 }, "speech": [ "<font color=\"#696969\">You dare use my own spells", "against me, Potter?</font>" ], "tokens": { "Harry": { "global": 85, "local": 1 } }, "switchCount": 25 }, { "lineNumber": 1411, "timeText": "02:20:06,149 --> 02:20:07,608", "timeEpoch": { "from": 8406149, "to": 8407608 }, "speech": [ "<font color=\"#696969\">Potter....</font>" ], "tokens": { "Harry": { "global": 86, "local": 1 } }, "switchCount": 25 }, { "lineNumber": 1414, "timeText": "02:20:17,513 --> 02:20:21,475", "timeEpoch": { "from": 8417513, "to": 8421475 }, "speech": [ "<font color=\"#696969\">You should know,", "Professor Dumbledore....</font>" ], "tokens": { "Dumbledore": { "global": 20, "local": 1 } }, "isSwitch": true, "switchCount": 26 }, { "lineNumber": 1436, "timeText": "02:22:06,260 --> 02:22:08,346", "timeEpoch": { "from": 8526260, "to": 8528346 }, "speech": [ "<font color=\"#696969\">Ron's okay with it, you know.</font>" ], "tokens": { "Ron": { "global": 44, "local": 1 } }, "switchCount": 26 }, { "lineNumber": 1439, "timeText": "02:22:16,061 --> 02:22:18,042", "timeEpoch": { "from": 8536061, "to": 8538042 }, "speech": [ "<font color=\"#696969\">I'm not coming back, Hermione.</font>" ], "tokens": { "Hermione": { "global": 11, "local": 1 } }, "switchCount": 26 }, { "lineNumber": 1440, "timeText": "02:22:19,189 --> 02:22:21,900", "timeEpoch": { "from": 8539189, "to": 8541900 }, "speech": [ "<font color=\"#696969\">I've got to finish", "whatever Dumbledore started.</font>" ], "tokens": { "Dumbledore": { "global": 21, "local": 1 } }, "isSwitch": true, "switchCount": 27 }, { "lineNumber": 1442, "timeText": "02:22:25,132 --> 02:22:28,677", "timeEpoch": { "from": 8545132, "to": 8548677 }, "speech": [ "<font color=\"#696969\">....but I'll let you and Ron know where I am when I can.</font>" ], "tokens": { "Ron": { "global": 45, "local": 1 } }, "switchCount": 27 }, { "lineNumber": 1443, "timeText": "02:22:30,032 --> 02:22:32,639", "timeEpoch": { "from": 8550032, "to": 8552639 }, "speech": [ "<font color=\"#696969\">I've always admired your courage, Harry.</font>" ], "tokens": { "Harry": { "global": 87, "local": 1 } }, "switchCount": 27 }, { "lineNumber": 1447, "timeText": "02:22:47,653 --> 02:22:49,217", "timeEpoch": { "from": 8567653, "to": 8569217 }, "speech": [ "<font color=\"#696969\">You need us, Harry.</font>" ], "tokens": { "Harry": { "global": 88, "local": 1 } }, "switchCount": 27 } ] }
